worker/__init__.py
worker/process.py
worker/worker.py
python_worker-2.2.4.dist-info/METADATA
python_worker-2.2.4.dist-info/WHEEL
python_worker-2.2.4.dist-info/top_level.txt
python_worker-2.2.4.dist-info/RECORD
