Metadata-Version: 2.1
Name: python-worker
Version: 2.2.4
Summary: Simplify and master control (run and stop) the python threads (workers)
Home-page: https://github.com/Danangjoyoo/python-worker
Author: danangjoyoo (Agus Danangjoyo)
Author-email: <agus.danangjoyo.blog@gmail.com>
Keywords: python,threading,worker,async worker,async thread,abort thread,thread stopper,thread manager,simple thread,thread monitor
Classifier: Development Status :: 5 - Production/Stable
Classifier: Intended Audience :: Developers
Classifier: Programming Language :: Python :: 3
Classifier: Operating System :: Unix
Classifier: Operating System :: MacOS :: MacOS X
Classifier: Operating System :: Microsoft :: Windows
